Workbook

Sheet Raw Data
A1: Region | B1: Store | C1: Category | D1: Product | E1: Month | F1: Units Sold | G1: Unit Price | H1: Unit Cost | I1: Revenue | J1: Cost | K1: Profit | L1: Margin
A2: Midwest | B2: Chicago | C2: Apparel | D2: Denim Jacket | E2: 45870 | F2: 18 | G2: 69.99 | H2: 34.01 | I2: =F2*G2 -> 1259.82 | J2: =F2*H2 -> 612.18 | K2: =I2-J2 -> 647.64 | L2: =IFERROR(K2/I2,0) -> 0.51407344
A3: Midwest | B3: Chicago | C3: Apparel | D3: Men's T-Shirt | E3: 45870 | F3: 16 | G3: 19.99 | H3: 9.18 | I3: =F3*G3 -> 319.84 | J3: =F3*H3 -> 146.88 | K3: =I3-J3 -> 172.96 | L3: =IFERROR(K3/I3,0) -> 0.54077039
A4: Midwest | B4: Chicago | C4: Apparel | D4: Running Shoes | E4: 45870 | F4: 12 | G4: 79.99 | H4: 39.06 | I4: =F4*G4 -> 959.88 | J4: =F4*H4 -> 468.72 | K4: =I4-J4 -> 491.16 | L4: =IFERROR(K4/I4,0) -> 0.51168896
A5: Midwest | B5: Chicago | C5: Apparel | D5: Women's Leggings | E5: 45870 | F5: 13 | G5: 34.99 | H5: 14.48 | I5: =F5*G5 -> 454.87 | J5: =F5*H5 -> 188.24 | K5: =I5-J5 -> 266.63 | L5: =IFERROR(K5/I5,0) -> 0.58616748
A6: Midwest | B6: Chicago | C6: Apparel | D6: Wool Sweater | E6: 45870 | F6: 11 | G6: 54.99 | H6: 24.21 | I6: =F6*G6 -> 604.89 | J6: =F6*H6 -> 266.31 | K6: =I6-J6 -> 338.58 | L6: =IFERROR(K6/I6,0) -> 0.55973813
A7: Midwest | B7: Chicago | C7: Beauty & Personal Care | D7: Electric Toothbrush | E7: 45870 | F7: 17 | G7: 44.99 | H7: 20.36 | I7: =F7*G7 -> 764.83 | J7: =F7*H7 -> 346.12 | K7: =I7-J7 -> 418.71 | L7: =IFERROR(K7/I7,0) -> 0.54745499
A8: Midwest | B8: Chicago | C8: Beauty & Personal Care | D8: Facial Cleanser | E8: 45870 | F8: 20 | G8: 14.99 | H8: 5.65 | I8: =F8*G8 -> 299.8 | J8: =F8*H8 -> 113 | K8: =I8-J8 -> 186.8 | L8: =IFERROR(K8/I8,0) -> 0.62308205
A9: Midwest | B9: Chicago | C9: Beauty & Personal Care | D9: Hair Dryer | E9: 45870 | F9: 11 | G9: 39.99 | H9: 16.59 | I9: =F9*G9 -> 439.89 | J9: =F9*H9 -> 182.49 | K9: =I9-J9 -> 257.4 | L9: =IFERROR(K9/I9,0) -> 0.58514629
A10: Midwest | B10: Chicago | C10: Beauty & Personal Care | D10: Moisturizer | E10: 45870 | F10: 14 | G10: 18.99 | H10: 7.77 | I10: =F10*G10 -> 265.86 | J10: =F10*H10 -> 108.78 | K10: =I10-J10 -> 157.08 | L10: =IFERROR(K10/I10,0) -> 0.59083728
A11: Midwest | B11: Chicago | C11: Beauty & Personal Care | D11: Perfume Set | E11: 45870 | F11: 15 | G11: 42.99 | H11: 15.85 | I11: =F11*G11 -> 644.85 | J11: =F11*H11 -> 237.75 | K11: =I11-J11 -> 407.1 | L11: =IFERROR(K11/I11,0) -> 0.63130961
A12: Midwest | B12: Chicago | C12: Electronics | D12: Bluetooth Speaker | E12: 45870 | F12: 13 | G12: 44.99 | H12: 27.73 | I12: =F12*G12 -> 584.87 | J12: =F12*H12 -> 360.49 | K12: =I12-J12 -> 224.38 | L12: =IFERROR(K12/I12,0) -> 0.38364081
A13: Midwest | B13: Chicago | C13: Electronics | D13: Portable Charger | E13: 45870 | F13: 13 | G13: 34.99 | H13: 23.02 | I13: =F13*G13 -> 454.87 | J13: =F13*H13 -> 299.26 | K13: =I13-J13 -> 155.61 | L13: =IFERROR(K13/I13,0) -> 0.34209774
... A2401: West | B2401: Seattle | C2401: Sports & Outdoors | D2401: Yoga Mat | E2401: 46204 | F2401: 13 | G2401: 24.99 | H2401: 13.14 | I2401: =F2401*G2401 -> 324.87 | J2401: =F2401*H2401 -> 170.82 | K2401: =I2401-J2401 -> 154.05 | L2401: =IFERROR(K2401/I2401,0) -> 0.47418968

Sheet Regional Summary
A1: Region | B1: Revenue | C1: Cost | D1: Profit | E1: Margin
A2: Northeast | B2: =SUMIFS('Raw Data'!$I:$I,'Raw Data'!$A:$A,A2) -> 444123.14 | C2: =SUMIFS('Raw Data'!$J:$J,'Raw Data'!$A:$A,A2) -> 253563.56 | D2: =B2-C2 -> 190559.58 | E2: =IFERROR(D2/B2,0) -> 0.42906924
A3: Southeast | B3: =SUMIFS('Raw Data'!$I:$I,'Raw Data'!$A:$A,A3) -> 415919.51 | C3: =SUMIFS('Raw Data'!$J:$J,'Raw Data'!$A:$A,A3) -> 236894.61 | D3: =B3-C3 -> 179024.9 | E3: =IFERROR(D3/B3,0) -> 0.4304316
A4: Midwest | B4: =SUMIFS('Raw Data'!$I:$I,'Raw Data'!$A:$A,A4) -> 229774.07 | C4: =SUMIFS('Raw Data'!$J:$J,'Raw Data'!$A:$A,A4) -> 130284.72 | D4: =B4-C4 -> 99489.35 | E4: =IFERROR(D4/B4,0) -> 0.43298772
A5: West | B5: =SUMIFS('Raw Data'!$I:$I,'Raw Data'!$A:$A,A5) -> 468366.64 | C5: =SUMIFS('Raw Data'!$J:$J,'Raw Data'!$A:$A,A5) -> 266528.7 | D5: =B5-C5 -> 201837.94 | E5: =IFERROR(D5/B5,0) -> 0.43094004
A6: Southwest | B6: =SUMIFS('Raw Data'!$I:$I,'Raw Data'!$A:$A,A6) -> 167909.99 | C6: =SUMIFS('Raw Data'!$J:$J,'Raw Data'!$A:$A,A6) -> 95790.04 | D6: =B6-C6 -> 72119.95 | E6: =IFERROR(D6/B6,0) -> 0.42951554

Sheet Category Summary
A1: Category | B1: Revenue | C1: Cost | D1: Profit | E1: Margin
A2: Electronics | B2: =SUMIFS('Raw Data'!$I:$I,'Raw Data'!$C:$C,A2) -> 505900.83 | C2: =SUMIFS('Raw Data'!$J:$J,'Raw Data'!$C:$C,A2) -> 329827.78 | D2: =B2-C2 -> 176073.05 | E2: =IFERROR(D2/B2,0) -> 0.34803867
A3: Apparel | B3: =SUMIFS('Raw Data'!$I:$I,'Raw Data'!$C:$C,A3) -> 368208.66 | C3: =SUMIFS('Raw Data'!$J:$J,'Raw Data'!$C:$C,A3) -> 171664.33 | D3: =B3-C3 -> 196544.33 | E3: =IFERROR(D3/B3,0) -> 0.53378519
A4: Home & Kitchen | B4: =SUMIFS('Raw Data'!$I:$I,'Raw Data'!$C:$C,A4) -> 278589.96 | C4: =SUMIFS('Raw Data'!$J:$J,'Raw Data'!$C:$C,A4) -> 197008.96 | D4: =B4-C4 -> 81581 | E4: =IFERROR(D4/B4,0) -> 0.29283539
A5: Beauty & Personal Care | B5: =SUMIFS('Raw Data'!$I:$I,'Raw Data'!$C:$C,A5) -> 227508.47 | C5: =SUMIFS('Raw Data'!$J:$J,'Raw Data'!$C:$C,A5) -> 93048.06 | D5: =B5-C5 -> 134460.41 | E5: =IFERROR(D5/B5,0) -> 0.59101277
A6: Sports & Outdoors | B6: =SUMIFS('Raw Data'!$I:$I,'Raw Data'!$C:$C,A6) -> 345885.43 | C6: =SUMIFS('Raw Data'!$J:$J,'Raw Data'!$C:$C,A6) -> 191512.5 | D6: =B6-C6 -> 154372.93 | E6: =IFERROR(D6/B6,0) -> 0.44631232

Sheet Monthly Trend
A1: Month | B1: Total Revenue | C1: Electronics Revenue | D1: Total Profit
A2: 45870 | B2: =SUMIFS('Raw Data'!$I:$I,'Raw Data'!$E:$E,A2) -> 144877.77 | C2: =SUMIFS('Raw Data'!$I:$I,'Raw Data'!$E:$E,A2,'Raw Data'!$C:$C,"Electronics") -> 37088.48 | D2: =SUMIFS('Raw Data'!$K:$K,'Raw Data'!$E:$E,A2) -> 63236.78
A3: 45901 | B3: =SUMIFS('Raw Data'!$I:$I,'Raw Data'!$E:$E,A3) -> 141926.99 | C3: =SUMIFS('Raw Data'!$I:$I,'Raw Data'!$E:$E,A3,'Raw Data'!$C:$C,"Electronics") -> 37808.28 | D3: =SUMIFS('Raw Data'!$K:$K,'Raw Data'!$E:$E,A3) -> 61504.65
A4: 45931 | B4: =SUMIFS('Raw Data'!$I:$I,'Raw Data'!$E:$E,A4) -> 141872.4 | C4: =SUMIFS('Raw Data'!$I:$I,'Raw Data'!$E:$E,A4,'Raw Data'!$C:$C,"Electronics") -> 32864.04 | D4: =SUMIFS('Raw Data'!$K:$K,'Raw Data'!$E:$E,A4) -> 62189.58
A5: 45962 | B5: =SUMIFS('Raw Data'!$I:$I,'Raw Data'!$E:$E,A5) -> 177997.59 | C5: =SUMIFS('Raw Data'!$I:$I,'Raw Data'!$E:$E,A5,'Raw Data'!$C:$C,"Electronics") -> 78906.06 | D5: =SUMIFS('Raw Data'!$K:$K,'Raw Data'!$E:$E,A5) -> 73852.14
A6: 45992 | B6: =SUMIFS('Raw Data'!$I:$I,'Raw Data'!$E:$E,A6) -> 197970.08 | C6: =SUMIFS('Raw Data'!$I:$I,'Raw Data'!$E:$E,A6,'Raw Data'!$C:$C,"Electronics") -> 93483.73 | D6: =SUMIFS('Raw Data'!$K:$K,'Raw Data'!$E:$E,A6) -> 80886.93
A7: 46023 | B7: =SUMIFS('Raw Data'!$I:$I,'Raw Data'!$E:$E,A7) -> 135230.11 | C7: =SUMIFS('Raw Data'!$I:$I,'Raw Data'!$E:$E,A7,'Raw Data'!$C:$C,"Electronics") -> 32074.28 | D7: =SUMIFS('Raw Data'!$K:$K,'Raw Data'!$E:$E,A7) -> 58799.15
A8: 46054 | B8: =SUMIFS('Raw Data'!$I:$I,'Raw Data'!$E:$E,A8) -> 129533.83 | C8: =SUMIFS('Raw Data'!$I:$I,'Raw Data'!$E:$E,A8,'Raw Data'!$C:$C,"Electronics") -> 32084.39 | D8: =SUMIFS('Raw Data'!$K:$K,'Raw Data'!$E:$E,A8) -> 56314.48
A9: 46082 | B9: =SUMIFS('Raw Data'!$I:$I,'Raw Data'!$E:$E,A9) -> 135598.26 | C9: =SUMIFS('Raw Data'!$I:$I,'Raw Data'!$E:$E,A9,'Raw Data'!$C:$C,"Electronics") -> 33029.05 | D9: =SUMIFS('Raw Data'!$K:$K,'Raw Data'!$E:$E,A9) -> 59142.27
A10: 46113 | B10: =SUMIFS('Raw Data'!$I:$I,'Raw Data'!$E:$E,A10) -> 136606.88 | C10: =SUMIFS('Raw Data'!$I:$I,'Raw Data'!$E:$E,A10,'Raw Data'!$C:$C,"Electronics") -> 34628.8 | D10: =SUMIFS('Raw Data'!$K:$K,'Raw Data'!$E:$E,A10) -> 59287.44
A11: 46143 | B11: =SUMIFS('Raw Data'!$I:$I,'Raw Data'!$E:$E,A11) -> 124501.81 | C11: =SUMIFS('Raw Data'!$I:$I,'Raw Data'!$E:$E,A11,'Raw Data'!$C:$C,"Electronics") -> 30809.65 | D11: =SUMIFS('Raw Data'!$K:$K,'Raw Data'!$E:$E,A11) -> 54503.99
A12: 46174 | B12: =SUMIFS('Raw Data'!$I:$I,'Raw Data'!$E:$E,A12) -> 128469.39 | C12: =SUMIFS('Raw Data'!$I:$I,'Raw Data'!$E:$E,A12,'Raw Data'!$C:$C,"Electronics") -> 32259.55 | D12: =SUMIFS('Raw Data'!$K:$K,'Raw Data'!$E:$E,A12) -> 56021.59
A13: 46204 | B13: =SUMIFS('Raw Data'!$I:$I,'Raw Data'!$E:$E,A13) -> 131508.24 | C13: =SUMIFS('Raw Data'!$I:$I,'Raw Data'!$E:$E,A13,'Raw Data'!$C:$C,"Electronics") -> 30864.52 | D13: =SUMIFS('Raw Data'!$K:$K,'Raw Data'!$E:$E,A13) -> 57292.72

Sheet Store Performance
A1: Store | B1: Region | C1: H1 Revenue (Aug-Jan) | D1: H2 Revenue (Feb-Jul) | E1: % Change H1->H2 | F1: Full-Year Revenue | G1: Full-Year Profit | H1: Margin
A2: New York | B2: =INDEX('Raw Data'!$A:$A,MATCH(A2,'Raw Data'!$B:$B,0)) -> Northeast | C2: =SUMIFS('Raw Data'!$I:$I,'Raw Data'!$B:$B,A2,'Raw Data'!$E:$E,">="&DATE(2025,8,1),'Raw Data'!$E:$E,"<"&DATE(2026,2,1)) -> 92183.88 | D2: =SUMIFS('Raw Data'!$I:$I,'Raw Data'!$B:$B,A2,'Raw Data'!$E:$E,">="&DATE(2026,2,1),'Raw Data'!$E:$E,"<"&DATE(2026,8,1)) -> 82910.42 | E2: =IFERROR((D2-C2)/C2,0) -> -0.10059741 | F2: =C2+D2 -> 175094.3 | G2: =SUMIFS('Raw Data'!$K:$K,'Raw Data'!$B:$B,A2) -> 75493.49 | H2: =IFERROR(G2/F2,0) -> 0.43115904
A3: Boston | B3: =INDEX('Raw Data'!$A:$A,MATCH(A3,'Raw Data'!$B:$B,0)) -> Northeast | C3: =SUMIFS('Raw Data'!$I:$I,'Raw Data'!$B:$B,A3,'Raw Data'!$E:$E,">="&DATE(2025,8,1),'Raw Data'!$E:$E,"<"&DATE(2026,2,1)) -> 142750.88 | D3: =SUMIFS('Raw Data'!$I:$I,'Raw Data'!$B:$B,A3,'Raw Data'!$E:$E,">="&DATE(2026,2,1),'Raw Data'!$E:$E,"<"&DATE(2026,8,1)) -> 126277.96 | E3: =IFERROR((D3-C3)/C3,0) -> -0.11539628 | F3: =C3+D3 -> 269028.84 | G3: =SUMIFS('Raw Data'!$K:$K,'Raw Data'!$B:$B,A3) -> 115066.09 | H3: =IFERROR(G3/F3,0) -> 0.42770913
A4: Atlanta | B4: =INDEX('Raw Data'!$A:$A,MATCH(A4,'Raw Data'!$B:$B,0)) -> Southeast | C4: =SUMIFS('Raw Data'!$I:$I,'Raw Data'!$B:$B,A4,'Raw Data'!$E:$E,">="&DATE(2025,8,1),'Raw Data'!$E:$E,"<"&DATE(2026,2,1)) -> 107573.86 | D4: =SUMIFS('Raw Data'!$I:$I,'Raw Data'!$B:$B,A4,'Raw Data'!$E:$E,">="&DATE(2026,2,1),'Raw Data'!$E:$E,"<"&DATE(2026,8,1)) -> 89663.5 | E4: =IFERROR((D4-C4)/C4,0) -> -0.16649361 | F4: =C4+D4 -> 197237.36 | G4: =SUMIFS('Raw Data'!$K:$K,'Raw Data'!$B:$B,A4) -> 84148.94 | H4: =IFERROR(G4/F4,0) -> 0.42663794
A5: Miami | B5: =INDEX('Raw Data'!$A:$A,MATCH(A5,'Raw Data'!$B:$B,0)) -> Southeast | C5: =SUMIFS('Raw Data'!$I:$I,'Raw Data'!$B:$B,A5,'Raw Data'!$E:$E,">="&DATE(2025,8,1),'Raw Data'!$E:$E,"<"&DATE(2026,2,1)) -> 139362.48 | D5: =SUMIFS('Raw Data'!$I:$I,'Raw Data'!$B:$B,A5,'Raw Data'!$E:$E,">="&DATE(2026,2,1),'Raw Data'!$E:$E,"<"&DATE(2026,8,1)) -> 79319.67 | E5: =IFERROR((D5-C5)/C5,0) -> -0.43083913 | F5: =C5+D5 -> 218682.15 | G5: =SUMIFS('Raw Data'!$K:$K,'Raw Data'!$B:$B,A5) -> 94875.96 | H5: =IFERROR(G5/F5,0) -> 0.43385324
A6: Chicago | B6: =INDEX('Raw Data'!$A:$A,MATCH(A6,'Raw Data'!$B:$B,0)) -> Midwest | C6: =SUMIFS('Raw Data'!$I:$I,'Raw Data'!$B:$B,A6,'Raw Data'!$E:$E,">="&DATE(2025,8,1),'Raw Data'!$E:$E,"<"&DATE(2026,2,1)) -> 117432.97 | D6: =SUMIFS('Raw Data'!$I:$I,'Raw Data'!$B:$B,A6,'Raw Data'!$E:$E,">="&DATE(2026,2,1),'Raw Data'!$E:$E,"<"&DATE(2026,8,1)) -> 112341.1 | E6: =IFERROR((D6-C6)/C6,0) -> -0.043359799 | F6: =C6+D6 -> 229774.07 | G6: =SUMIFS('Raw Data'!$K:$K,'Raw Data'!$B:$B,A6) -> 99489.35 | H6: =IFERROR(G6/F6,0) -> 0.43298772
A7: Los Angeles | B7: =INDEX('Raw Data'!$A:$A,MATCH(A7,'Raw Data'!$B:$B,0)) -> West | C7: =SUMIFS('Raw Data'!$I:$I,'Raw Data'!$B:$B,A7,'Raw Data'!$E:$E,">="&DATE(2025,8,1),'Raw Data'!$E:$E,"<"&DATE(2026,2,1)) -> 116015.06 | D7: =SUMIFS('Raw Data'!$I:$I,'Raw Data'!$B:$B,A7,'Raw Data'!$E:$E,">="&DATE(2026,2,1),'Raw Data'!$E:$E,"<"&DATE(2026,8,1)) -> 103471.75 | E7: =IFERROR((D7-C7)/C7,0) -> -0.10811795 | F7: =C7+D7 -> 219486.81 | G7: =SUMIFS('Raw Data'!$K:$K,'Raw Data'!$B:$B,A7) -> 95062.61 | H7: =IFERROR(G7/F7,0) -> 0.43311309
A8: Seattle | B8: =INDEX('Raw Data'!$A:$A,MATCH(A8,'Raw Data'!$B:$B,0)) -> West | C8: =SUMIFS('Raw Data'!$I:$I,'Raw Data'!$B:$B,A8,'Raw Data'!$E:$E,">="&DATE(2025,8,1),'Raw Data'!$E:$E,"<"&DATE(2026,2,1)) -> 134860.09 | D8: =SUMIFS('Raw Data'!$I:$I,'Raw Data'!$B:$B,A8,'Raw Data'!$E:$E,">="&DATE(2026,2,1),'Raw Data'!$E:$E,"<"&DATE(2026,8,1)) -> 114019.74 | E8: =IFERROR((D8-C8)/C8,0) -> -0.15453312 | F8: =C8+D8 -> 248879.83 | G8: =SUMIFS('Raw Data'!$K:$K,'Raw Data'!$B:$B,A8) -> 106775.33 | H8: =IFERROR(G8/F8,0) -> 0.42902364
A9: Dallas | B9: =INDEX('Raw Data'!$A:$A,MATCH(A9,'Raw Data'!$B:$B,0)) -> Southwest | C9: =SUMIFS('Raw Data'!$I:$I,'Raw Data'!$B:$B,A9,'Raw Data'!$E:$E,">="&DATE(2025,8,1),'Raw Data'!$E:$E,"<"&DATE(2026,2,1)) -> 89695.72 | D9: =SUMIFS('Raw Data'!$I:$I,'Raw Data'!$B:$B,A9,'Raw Data'!$E:$E,">="&DATE(2026,2,1),'Raw Data'!$E:$E,"<"&DATE(2026,8,1)) -> 78214.27 | E9: =IFERROR((D9-C9)/C9,0) -> -0.12800444 | F9: =C9+D9 -> 167909.99 | G9: =SUMIFS('Raw Data'!$K:$K,'Raw Data'!$B:$B,A9) -> 72119.95 | H9: =IFERROR(G9/F9,0) -> 0.42951554

Sheet Product Summary
A1: Product | B1: Category | C1: Revenue | D1: Profit | E1: Margin
A2: Wireless Earbuds | B2: =INDEX('Raw Data'!$C:$C,MATCH(A2,'Raw Data'!$D:$D,0)) -> Electronics | C2: =SUMIFS('Raw Data'!$I:$I,'Raw Data'!$D:$D,A2) -> 108881.85 | D2: =SUMIFS('Raw Data'!$K:$K,'Raw Data'!$D:$D,A2) -> 38019.65 | E2: =IFERROR(D2/C2,0) -> 0.34918262
A3: Bluetooth Speaker | B3: =INDEX('Raw Data'!$C:$C,MATCH(A3,'Raw Data'!$D:$D,0)) -> Electronics | C3: =SUMIFS('Raw Data'!$I:$I,'Raw Data'!$D:$D,A3) -> 79182.4 | D3: =SUMIFS('Raw Data'!$K:$K,'Raw Data'!$D:$D,A3) -> 30195.22 | E3: =IFERROR(D3/C3,0) -> 0.38133752
A4: Smartwatch | B4: =INDEX('Raw Data'!$C:$C,MATCH(A4,'Raw Data'!$D:$D,0)) -> Electronics | C4: =SUMIFS('Raw Data'!$I:$I,'Raw Data'!$D:$D,A4) -> 210702.44 | D4: =SUMIFS('Raw Data'!$K:$K,'Raw Data'!$D:$D,A4) -> 67324.93 | E4: =IFERROR(D4/C4,0) -> 0.31952611
A5: Tablet Stand | B5: =INDEX('Raw Data'!$C:$C,MATCH(A5,'Raw Data'!$D:$D,0)) -> Electronics | C5: =SUMIFS('Raw Data'!$I:$I,'Raw Data'!$D:$D,A5) -> 45831.66 | D5: =SUMIFS('Raw Data'!$K:$K,'Raw Data'!$D:$D,A5) -> 18404.32 | E5: =IFERROR(D5/C5,0) -> 0.40156346
A6: Portable Charger | B6: =INDEX('Raw Data'!$C:$C,MATCH(A6,'Raw Data'!$D:$D,0)) -> Electronics | C6: =SUMIFS('Raw Data'!$I:$I,'Raw Data'!$D:$D,A6) -> 61302.48 | D6: =SUMIFS('Raw Data'!$K:$K,'Raw Data'!$D:$D,A6) -> 22128.93 | E6: =IFERROR(D6/C6,0) -> 0.36097936
A7: Men's T-Shirt | B7: =INDEX('Raw Data'!$C:$C,MATCH(A7,'Raw Data'!$D:$D,0)) -> Apparel | C7: =SUMIFS('Raw Data'!$I:$I,'Raw Data'!$D:$D,A7) -> 28865.56 | D7: =SUMIFS('Raw Data'!$K:$K,'Raw Data'!$D:$D,A7) -> 15869.54 | E7: =IFERROR(D7/C7,0) -> 0.54977419
A8: Women's Leggings | B8: =INDEX('Raw Data'!$C:$C,MATCH(A8,'Raw Data'!$D:$D,0)) -> Apparel | C8: =SUMIFS('Raw Data'!$I:$I,'Raw Data'!$D:$D,A8) -> 50805.48 | D8: =SUMIFS('Raw Data'!$K:$K,'Raw Data'!$D:$D,A8) -> 29491.31 | E8: =IFERROR(D8/C8,0) -> 0.58047498
A9: Denim Jacket | B9: =INDEX('Raw Data'!$C:$C,MATCH(A9,'Raw Data'!$D:$D,0)) -> Apparel | C9: =SUMIFS('Raw Data'!$I:$I,'Raw Data'!$D:$D,A9) -> 98755.89 | D9: =SUMIFS('Raw Data'!$K:$K,'Raw Data'!$D:$D,A9) -> 51343.21 | E9: =IFERROR(D9/C9,0) -> 0.51990023
A10: Running Shoes | B10: =INDEX('Raw Data'!$C:$C,MATCH(A10,'Raw Data'!$D:$D,0)) -> Apparel | C10: =SUMIFS('Raw Data'!$I:$I,'Raw Data'!$D:$D,A10) -> 109826.27 | D10: =SUMIFS('Raw Data'!$K:$K,'Raw Data'!$D:$D,A10) -> 55070.97 | E10: =IFERROR(D10/C10,0) -> 0.50143713
A11: Wool Sweater | B11: =INDEX('Raw Data'!$C:$C,MATCH(A11,'Raw Data'!$D:$D,0)) -> Apparel | C11: =SUMIFS('Raw Data'!$I:$I,'Raw Data'!$D:$D,A11) -> 79955.46 | D11: =SUMIFS('Raw Data'!$K:$K,'Raw Data'!$D:$D,A11) -> 44769.3 | E11: =IFERROR(D11/C11,0) -> 0.55992799
A12: Coffee Maker | B12: =INDEX('Raw Data'!$C:$C,MATCH(A12,'Raw Data'!$D:$D,0)) -> Home & Kitchen | C12: =SUMIFS('Raw Data'!$I:$I,'Raw Data'!$D:$D,A12) -> 71335.73 | D12: =SUMIFS('Raw Data'!$K:$K,'Raw Data'!$D:$D,A12) -> 19869.13 | E12: =IFERROR(D12/C12,0) -> 0.27852985
A13: Non-Stick Pan Set | B13: =INDEX('Raw Data'!$C:$C,MATCH(A13,'Raw Data'!$D:$D,0)) -> Home & Kitchen | C13: =SUMIFS('Raw Data'!$I:$I,'Raw Data'!$D:$D,A13) -> 92220.81 | D13: =SUMIFS('Raw Data'!$K:$K,'Raw Data'!$D:$D,A13) -> 27685.68 | E13: =IFERROR(D13/C13,0) -> 0.30021077
... A26: Hiking Backpack | B26: =INDEX('Raw Data'!$C:$C,MATCH(A26,'Raw Data'!$D:$D,0)) -> Sports & Outdoors | C26: =SUMIFS('Raw Data'!$I:$I,'Raw Data'!$D:$D,A26) -> 96662.11 | D26: =SUMIFS('Raw Data'!$K:$K,'Raw Data'!$D:$D,A26) -> 43406.96 | E26: =IFERROR(D26/C26,0) -> 0.44905868
A28: Top 5 Products by Revenue
A29: Rank | B29: Product | C29: Revenue
A30: 1 | B30: =INDEX($A$2:$A$26,MATCH(C30,$C$2:$C$26,0)) -> Smartwatch | C30: =LARGE($C$2:$C$26,1) -> 210702.44
A31: 2 | B31: =INDEX($A$2:$A$26,MATCH(C31,$C$2:$C$26,0)) -> Camping Tent | C31: =LARGE($C$2:$C$26,2) -> 166907.16
A32: 3 | B32: =INDEX($A$2:$A$26,MATCH(C32,$C$2:$C$26,0)) -> Running Shoes | C32: =LARGE($C$2:$C$26,3) -> 109826.27
A33: 4 | B33: =INDEX($A$2:$A$26,MATCH(C33,$C$2:$C$26,0)) -> Wireless Earbuds | C33: =LARGE($C$2:$C$26,4) -> 108881.85
A34: 5 | B34: =INDEX($A$2:$A$26,MATCH(C34,$C$2:$C$26,0)) -> Denim Jacket | C34: =LARGE($C$2:$C$26,5) -> 98755.89
A35: Bottom 5 Products by Revenue
A36: Rank | B36: Product | C36: Revenue
A37: 1 | B37: =INDEX($A$2:$A$26,MATCH(C37,$C$2:$C$26,0)) -> Facial Cleanser | C37: =SMALL($C$2:$C$26,1) -> 22095.26
A38: 2 | B38: =INDEX($A$2:$A$26,MATCH(C38,$C$2:$C$26,0)) -> Water Bottle | C38: =SMALL($C$2:$C$26,2) -> 22307.87
A39: 3 | B39: =INDEX($A$2:$A$26,MATCH(C39,$C$2:$C$26,0)) -> Moisturizer | C39: =SMALL($C$2:$C$26,3) -> 26073.27
A40: 4 | B40: =INDEX($A$2:$A$26,MATCH(C40,$C$2:$C$26,0)) -> Resistance Bands | C40: =SMALL($C$2:$C$26,4) -> 26946.52
A41: 5 | B41: =INDEX($A$2:$A$26,MATCH(C41,$C$2:$C$26,0)) -> Men's T-Shirt | C41: =SMALL($C$2:$C$26,5) -> 28865.56

Sheet Insights & Recommendations
A1: Northwind Retail — Sales Performance: Key Findings
A2: All figures below are computed live via formulas from the Raw Data sheet.
A4: Total Revenue (FY) | B4: =SUM('Raw Data'!$I:$I) -> 1726093.4
A5: Total Profit (FY) | B5: =SUM('Raw Data'!$K:$K) -> 743031.72
A6: Overall Margin | B6: =B5/B4 -> 0.43047018
A7: Top Region | B7: =INDEX('Regional Summary'!$A$2:$A$6,MATCH(MAX('Regional Summary'!$B$2:$B$6),'Regional Summary'!$B$2:$B$6,0)) -> West
A8: Top Region Revenue | B8: =MAX('Regional Summary'!$B$2:$B$6) -> 468366.64
A9: Bottom Region | B9: =INDEX('Regional Summary'!$A$2:$A$6,MATCH(MIN('Regional Summary'!$B$2:$B$6),'Regional Summary'!$B$2:$B$6,0)) -> Southwest
A10: Bottom Region Revenue | B10: =MIN('Regional Summary'!$B$2:$B$6) -> 167909.99
A11: Most Declining Store (H1->H2) | B11: =INDEX('Store Performance'!$A$2:$A$9,MATCH(MIN('Store Performance'!$E$2:$E$9),'Store Performance'!$E$2:$E$9,0)) -> Miami
A12: Decline % | B12: =MIN('Store Performance'!$E$2:$E$9) -> -0.43083913
A13: Thinnest-Margin Category | B13: =INDEX('Category Summary'!$A$2:$A$6,MATCH(MIN('Category Summary'!$E$2:$E$6),'Category Summary'!$E$2:$E$6,0)) -> Home & Kitchen
A14: Thinnest Margin % | B14: =MIN('Category Summary'!$E$2:$E$6) -> 0.29283539
A15: Electronics Holiday Lift (Nov/Dec vs. rest of year) | B15: =AVERAGE('Monthly Trend'!$C$5:$C$6)/AVERAGE('Monthly Trend'!$C$2:$C$4,'Monthly Trend'!$C$7:$C$13)-1 -> 1.584469
A17: Findings & Recommendations
A18: (Analyst commentary — see the Key Metrics above and the underlying sheets for the figures cited.)
A20: 1. Miami is in a steady, accelerating decline.
A21: Miami's revenue fell roughly 43% from the first half of the year to the second half, the steepest drop of any store, while every other Southeast store held steady or grew. This reads as a competitive or local-demand problem, not a seasonal blip. Recommend an on-the-ground review (new competitor activity, pricing, foot traffic) within the next quarter, paired with a targeted local promotion to test whether discounting recovers volume before considering a footprint change.
A23: 2. Dallas is dramatically underperforming in Sports & Outdoors specifically.
A24: Dallas sells about 75% less Sports & Outdoors merchandise than the average of the other stores, while its performance in every other category is in line with peers — so this isn't a store-wide problem. Recommend auditing local assortment and shelf placement for that category, and testing regional marketing (e.g. tying inventory to local outdoor/sports seasonality in Texas) before cutting shelf space.
A26: 3. Home & Kitchen carries the thinnest margin of any category.
A27: At roughly a 29% margin versus 53-59% for Apparel and Beauty & Personal Care, Home & Kitchen is the category most exposed to cost inflation. Recommend a supplier/cost review for this category and testing a modest price increase on the highest-volume SKUs, where demand is least likely to be price-sensitive.
A29: 4. Electronics spikes sharply in November and December.
A30: Electronics revenue in Nov/Dec runs well above the rest-of-year average, consistent with holiday shopping. Recommend building this into inventory and staffing plans ahead of Q4 rather than reacting to it, and considering a complementary cross-sell push (accessories, extended warranties) during that window to capture additional margin.
A32: 5. Apparel and Beauty & Personal Care are the strongest all-around performers.
A33: Both combine solid revenue with the highest margins in the portfolio. Recommend protecting and growing shelf space/marketing spend for these categories, and using them as the template (assortment, pricing approach) when reviewing the weaker categories above.
